{"books":[{"title":"The Brothers Karamazov","requirement":"Required","isbn":"9780374528379 | 0374528373","author":"Fyodor Dostoevsky"},{"title":"Fathers and Sons (Penguin Classics)","requirement":"Required","isbn":"9780141441337 | 014144133X","author":"Ivan Turgenev"},{"title":"Gulliver's Travels (Penguin Classics)","requirement":"Required","isbn":"9780141439495 | 0141439491","author":"Jonathan Swift"},{"title":"Hamlet (The New Folger Library Shakespeare)","requirement":"Required","isbn":"9780743477123 | 074347712X","author":"William Shakespeare"},{"title":"The Odyssey (Penguin Classics)","requirement":"Required","isbn":"9780143039952 | 0143039954","author":"Homer"}],"course_number":"76-221"}